fast_bitrix24/__init__.py
fast_bitrix24/__version__.py
fast_bitrix24/bitrix.py
fast_bitrix24/logger.py
fast_bitrix24/mult_request.py
fast_bitrix24/server_response.py
fast_bitrix24/srh.py
fast_bitrix24/throttle.py
fast_bitrix24/user_request.py
fast_bitrix24/utils.py
fast_bitrix24-1.8.11.dist-info/licenses/LICENSE
fast_bitrix24-1.8.11.dist-info/METADATA
fast_bitrix24-1.8.11.dist-info/WHEEL
fast_bitrix24-1.8.11.dist-info/top_level.txt
fast_bitrix24-1.8.11.dist-info/RECORD
