Metadata-Version: 2.4
Name: fast_bitrix24
Version: 1.8.11
Summary: API wrapper для быстрого получения данных от Битрикс24 через REST API. Параллельные запросы к серверу, упаковка запросов в батчи, контроль скорости запросов, есть синхронный и асинхронный клиенты.
Home-page: https://github.com/leshchenko1979/fast_bitrix24
Author: Alexey Leshchenko
Author-email: leshchenko@gmail.com
License: MIT
Classifier: Programming Language :: Python :: 3
Classifier: License :: OSI Approved :: MIT License
Classifier: Operating System :: OS Independent
Requires-Python: >=3.7
License-File: LICENSE
Requires-Dist: aiohttp
Requires-Dist: tqdm
Requires-Dist: more_itertools
Requires-Dist: icontract
Requires-Dist: beartype>=0.10.0
Dynamic: author
Dynamic: author-email
Dynamic: classifier
Dynamic: description
Dynamic: description-content-type
Dynamic: home-page
Dynamic: license
Dynamic: license-file
Dynamic: requires-dist
Dynamic: requires-python
Dynamic: summary
